cymongo.py
cymongo-0.1.dist-info/DESCRIPTION.rst
cymongo-0.1.dist-info/METADATA
cymongo-0.1.dist-info/RECORD
cymongo-0.1.dist-info/WHEEL
cymongo-0.1.dist-info/metadata.json
cymongo-0.1.dist-info/top_level.txt
