Metadata-Version: 2.0
Name: cymongo
Version: 0.1
Summary: Much faster than pymongo.
Home-page: UNKNOWN
Author: Huang Qiangsheng
Author-email: hqsh@live.cn
License: UNKNOWN
Platform: UNKNOWN
Classifier: Development Status :: 5 - Production/Stable
Classifier: Environment :: Web Environment
Classifier: Intended Audience :: Developers
Classifier: Operating System :: OS Independent
Classifier: Programming Language :: Python
Classifier: Programming Language :: Python :: 2
Classifier: Programming Language :: Python :: 3
Classifier: Topic :: Software Development :: Libraries :: Python Modules
Requires-Dist: numpy
Requires-Dist: pandas
